{
	"instance" : {
		"idleClients" : "SebastianSastre 5/3/2014 17:22:48",
		"remove:" : "SebastianSastre 5/3/2014 17:22:48",
		"initializeIdleClients" : "SebastianSastre 5/3/2014 17:22:48",
		"hasIdleClients" : "SebastianSastre 5/3/2014 17:22:48",
		"username" : "AutoDeprecationRefactoring 9/11/2019 12:42",
		"withClientDo:" : "sebastiansastre 6/23/2019 20:18",
		"busyClients" : "SebastianSastre 5/3/2014 17:22:48",
		"initializeBusyClients" : "SebastianSastre 5/3/2014 17:22:48",
		"clientsMutex" : "SebastianSastre 5/3/2014 17:22:48",
		"hasBusyClients" : "SebastianSastre 5/3/2014 17:22:48",
		"requestClient" : "sebastiansastre 6/23/2019 20:18",
		"reset" : "SebastianSastre 5/3/2014 17:22:48",
		"currentClientDynamicVariable" : "SebastianSastre 5/3/2014 17:22:48",
		"databaseName" : "sebastiansastre 6/18/2019 23:23",
		"do:" : "SebastianSastre 5/3/2014 17:22:48",
		"authenticationDatabaseName" : "AutoDeprecationRefactoring 9/11/2019 12:42",
		"returnClient:" : "sebastiansastre 6/23/2019 20:18",
		"makeClient" : "SebastianSastre 5/3/2014 17:22:48",
		"logNewClient:" : "sebastiansastre 6/23/2019 20:17",
		"hasClients" : "SebastianSastre 5/3/2014 17:22:48",
		"password" : "AutoDeprecationRefactoring 9/11/2019 12:42",
		"printOn:" : "SebastianSastre 5/3/2014 17:22:48",
		"returningUnusedClient" : "SebastianSastre 5/3/2014 17:22:48",
		"initializeClientsMutex" : "SebastianSastre 5/3/2014 17:22:48"
	},
	"class" : {
		"initializeInstance" : "SebastianSastre 5/3/2014 17:22:48",
		"instance" : "SebastianSastre 5/3/2014 17:22:48",
		"reset" : "SebastianSastre 5/3/2014 17:22:48"
	}
}