{
	"class" : {
		"database" : "SebastianSastre 7/7/2014 17:48:35",
		"findAll" : "SebastianSastre 7/7/2014 17:48:35",
		"findAllSortedBy:" : "SebastianSastre 7/7/2014 17:48:35",
		"findId:" : "SebastianSastre 7/7/2014 17:48:35",
		"fromBSON:" : "SebastianSastre 7/7/2014 17:48:35",
		"fromJSON:" : "SebastianSastre 7/7/2014 17:48:35",
		"fromJSONObject:" : "sebastiansastre 7/7/2014 18:58",
		"fromJSONObjects:" : "SebastianSastre 7/7/2014 17:48:35",
		"fromJSONString:" : "SebastianSastre 7/7/2014 17:48:35",
		"fromReified:" : "SebastianSastre 7/7/2014 17:48:35",
		"isAbstract" : "SebastianSastre 7/7/2014 17:48:35",
		"isDeprecated" : "SebastianSastre 7/7/2014 17:48:35",
		"keysToExclude" : "SebastianSastre 7/7/2014 17:48:35",
		"makeId" : "SebastianSastre 7/7/2014 17:48:35",
		"modelClasses" : "SebastianSastre 7/7/2014 17:48:35",
		"pluralName" : "sebastiansastre 8/10/2014 17:12",
		"singularName" : "sebastiansastre 8/10/2014 17:19" },
	"instance" : {
		"=" : "sebastiansastre 7/7/2014 19:10",
		"asBSON" : "SebastianSastre 7/7/2014 17:48:35",
		"asBSONFriendly" : "SebastianSastre 7/7/2014 17:48:35",
		"asDictionary" : "SebastianSastre 7/7/2014 17:48:35",
		"asJSONString" : "SebastianSastre 7/7/2014 17:48:35",
		"asNoSQLValue" : "SebastianSastre 7/7/2014 17:48:35",
		"at:" : "SebastianSastre 7/7/2014 17:48:35",
		"at:put:" : "SebastianSastre 7/7/2014 17:48:35",
		"copyFrom:" : "SebastianSastre 7/7/2014 17:48:35",
		"createdOn" : "SebastianSastre 7/7/2014 17:48:35",
		"data" : "SebastianSastre 7/7/2014 17:48:35",
		"data:" : "SebastianSastre 7/7/2014 17:48:35",
		"dateAndTimeAt:" : "SebastianSastre 7/7/2014 17:48:35",
		"doesNotUnderstand:" : "SebastianSastre 7/7/2014 17:48:35",
		"ensureId" : "SebastianSastre 7/7/2014 17:48:35",
		"fresh" : "SebastianSastre 7/7/2014 17:48:35",
		"initializeData" : "SebastianSastre 7/7/2014 17:48:35",
		"initializeOn:" : "sebastiansastre 8/2/2014 22:32",
		"isPersistentModel" : "SebastianSastre 7/7/2014 17:48:35",
		"isReifiedJSON:" : "SebastianSastre 7/7/2014 17:48:35",
		"isUnsaved" : "SebastianSastre 7/7/2014 17:48:35",
		"jsonWriteOn:" : "SebastianSastre 7/7/2014 17:48:35",
		"merge:" : "SebastianSastre 7/7/2014 17:48:35",
		"onAboutToJSON" : "SebastianSastre 7/7/2014 17:48:35",
		"onRead" : "SebastianSastre 7/7/2014 17:48:35",
		"raw" : "SebastianSastre 7/7/2014 17:48:35",
		"raw:" : "SebastianSastre 7/7/2014 17:48:35",
		"sanitize:" : "SebastianSastre 7/7/2014 17:48:35",
		"subModelAt:" : "SebastianSastre 7/7/2014 17:48:35" } }
